simplepgsql/README.md
simplepgsql/__init__.py
simplepgsql/build_query.py
simplepgsql/depr_simplepgsql.py
simplepgsql/labels.py
simplepgsql/pgsql_wizard.py
simplepgsql/simplepgsql.py
simplepgsql/wip_simplepgsql.py
simplepgsql/formatters/__init__.py
simplepgsql/formatters/array_formatter.py
simplepgsql-0.1.13.dist-info/METADATA
simplepgsql-0.1.13.dist-info/WHEEL
simplepgsql-0.1.13.dist-info/licenses/LICENSE
simplepgsql-0.1.13.dist-info/RECORD
