Metadata-Version: 2.4
Name: simplepgsql
Version: 0.1.13
Summary: Wrapper around psycopg2 to simplify the process of connecting to a PostgreSQL database and executing queries.
Project-URL: Repository, https://github.com/iamlrk/simple-pgsql
Author-email: iamlrk <lepakshiramkiran@hotmail.com>
License:                     GNU GENERAL PUBLIC LICENSE
License-File: LICENSE
Keywords: database,pgsql,psql,psycopg2,python,simple-psql,wrapper
Classifier: Development Status :: 4 - Beta
Classifier: License :: OSI Approved :: GNU General Public License v3 (GPLv3)
Classifier: Operating System :: OS Independent
Classifier: Programming Language :: Python :: 3
Classifier: Programming Language :: SQL
